{
    "target": "com.apple.driver.AppleT8027TypeCPhy",
    "total": 20,
    "version": {
        "max": "25.5.0",
        "min": "25.4.0"
    },
    "signatures": [
        {
            "args": 0,
            "anchors": [
                {
                    "string": "usb3-phy-lane",
                    "segment": "__TEXT",
                    "section": "__cstring",
                    "caller": "_snprintf"
                },
                {
                    "string": "%s@%s: %s::%s: _usb3PhyLane %d\n",
                    "segment": "__TEXT",
                    "section": "__cstring",
                    "caller": "_snprintf"
                },
                {
                    "string": "usb3-phy-parent",
                    "segment": "__TEXT",
                    "section": "__cstring",
                    "caller": "__os_log_internal"
                },
                {
                    "string": "AAPL,phandle",
                    "segment": "__TEXT",
                    "section": "__cstring",
                    "caller": "__ZN8OSSymbol11withCStringEPKc"
                },
                {
                    "string": "%s@%s: %s::%s: did not find _usb3Phy\n",
                    "segment": "__TEXT",
                    "section": "__cstring",
                    "caller": "_IOLog"
                },
                {
                    "string": "%s@%s: %s::%s: usb3-phy-parent not specified\n",
                    "segment": "__TEXT",
                    "section": "__cstring",
                    "caller": "_IOLog"
                },
                {
                    "string": "%s@%s: %s::%s: _usb3PhyLane %d\n",
                    "segment": "__TEXT",
                    "section": "__os_log",
                    "caller": "_snprintf"
                },
                {
                    "string": "%s@%s: %s::%s: did not find _usb3Phy\n",
                    "segment": "__TEXT",
                    "section": "__os_log",
                    "caller": "__os_log_internal"
                },
                {
                    "string": "%s@%s: %s::%s: usb3-phy-parent not specified\n",
                    "segment": "__TEXT",
                    "section": "__os_log",
                    "caller": "__os_log_internal"
                }
            ],
            "symbol": "__ZN18AppleT8027TypeCPhy5startEP9IOService",
            "prototype": "",
            "backtrace": [],
            "provenance": "direct"
        },
        {
            "args": 0,
            "anchors": [
                {
                    "string": "tunable-host",
                    "segment": "__TEXT",
                    "section": "__cstring",
                    "caller": "__ZN15OSMetaClassBase12safeMetaCastEPKS_PK11OSMetaClass"
                },
                {
                    "string": "tunable-device",
                    "segment": "__TEXT",
                    "section": "__cstring",
                    "caller": "__ZN15OSMetaClassBase12safeMetaCastEPKS_PK11OSMetaClass"
                }
            ],
            "symbol": "__ZN18AppleT8027TypeCPhy13configureUSB2E23AppleTypeCPhyPowerLevelj",
            "prototype": "",
            "backtrace": [],
            "provenance": "direct"
        },
        {
            "args": 0,
            "anchors": [
                {
                    "string": "%s@%s: %s::%s: tunable range %d invalid\n",
                    "segment": "__TEXT",
                    "section": "__cstring",
                    "caller": "__os_log_internal"
                },
                {
                    "string": "%s@%s: %s::%s: tunable range %d offset 0x%08x invalid (rangeLength 0x%08llx)\n",
                    "segment": "__TEXT",
                    "section": "__cstring",
                    "caller": "__os_log_internal"
                },
                {
                    "string": "%s@%s: %s::%s: tunable range %d offset 0x%08x mask 0x%08x value 0x%08x already set (read 0x%08x)\n",
                    "segment": "__TEXT",
                    "section": "__cstring",
                    "caller": "__os_log_internal"
                },
                {
                    "string": "%s@%s: %s::%s: tunable range %d offset 0x%08x mask 0x%08x value 0x%08x (read 0x%08x wrote 0x%08x)\n",
                    "segment": "__TEXT",
                    "section": "__cstring",
                    "caller": "__os_log_internal"
                },
                {
                    "string": "%s@%s: %s::%s: tunable range %d invalid\n",
                    "segment": "__TEXT",
                    "section": "__os_log",
                    "caller": "__os_log_internal"
                },
                {
                    "string": "%s@%s: %s::%s: tunable range %d offset 0x%08x invalid (rangeLength 0x%08llx)\n",
                    "segment": "__TEXT",
                    "section": "__os_log",
                    "caller": "__os_log_internal"
                },
                {
                    "string": "%s@%s: %s::%s: tunable range %d offset 0x%08x mask 0x%08x value 0x%08x already set (read 0x%08x)\n",
                    "segment": "__TEXT",
                    "section": "__os_log",
                    "caller": "__os_log_internal"
                },
                {
                    "string": "%s@%s: %s::%s: tunable range %d offset 0x%08x mask 0x%08x value 0x%08x (read 0x%08x wrote 0x%08x)\n",
                    "segment": "__TEXT",
                    "section": "__os_log",
                    "caller": "__os_log_internal"
                }
            ],
            "symbol": "__ZN18AppleT8027TypeCPhy17applyTunablesUSB2EPK6OSData",
            "prototype": "",
            "backtrace": [],
            "provenance": "direct"
        },
        {
            "args": 0,
            "anchors": [
                {
                    "string": "%s: %s::%s: failed to find register range index %d\n",
                    "segment": "__TEXT",
                    "section": "__cstring",
                    "caller": "_IOLog"
                },
                {
                    "string": "low-leakage-disable",
                    "segment": "__TEXT",
                    "section": "__cstring",
                    "caller": "__os_log_internal"
                },
                {
                    "string": "%s: %s::%s: low leakage mode disabled\n",
                    "segment": "__TEXT",
                    "section": "__cstring",
                    "caller": "_IOLog"
                },
                {
                    "string": "%s: %s::%s: failed to find register range index %d\n",
                    "segment": "__TEXT",
                    "section": "__os_log",
                    "caller": "__os_log_internal"
                },
                {
                    "string": "%s: %s::%s: low leakage mode disabled\n",
                    "segment": "__TEXT",
                    "section": "__os_log",
                    "caller": "__os_log_internal"
                }
            ],
            "symbol": "__ZN17AppleT8027USB3Phy5startEP9IOService",
            "prototype": "",
            "backtrace": [],
            "provenance": "direct"
        },
        {
            "args": 0,
            "anchors": [
                {
                    "string": " @%s:%d",
                    "segment": "__TEXT",
                    "section": "__cstring",
                    "caller": "_panic"
                }
            ],
            "symbol": "_OUTLINED_FUNCTION_0",
            "prototype": "",
            "backtrace": [
                "_panic"
            ],
            "provenance": "direct"
        },
        {
            "args": 0,
            "anchors": [
                {
                    "string": "%s: %s::%s: system sleep\n",
                    "segment": "__TEXT",
                    "section": "__cstring",
                    "caller": "_IOLog"
                },
                {
                    "string": "%s: %s::%s: system sleep\n",
                    "segment": "__TEXT",
                    "section": "__os_log",
                    "caller": "__os_log_internal"
                }
            ],
            "symbol": "__ZN17AppleT8027USB3Phy22powerStateWillChangeToEmmP9IOService",
            "prototype": "",
            "backtrace": [],
            "provenance": "direct"
        },
        {
            "args": 0,
            "anchors": [
                {
                    "string": "%s: %s::%s: system wake\n",
                    "segment": "__TEXT",
                    "section": "__cstring",
                    "caller": "_IOLog"
                },
                {
                    "string": "%s: %s::%s: system wake\n",
                    "segment": "__TEXT",
                    "section": "__os_log",
                    "caller": "__os_log_internal"
                }
            ],
            "symbol": "__ZN17AppleT8027USB3Phy21powerStateDidChangeToEmmP9IOService",
            "prototype": "",
            "backtrace": [],
            "provenance": "direct"
        },
        {
            "args": 0,
            "anchors": [
                {
                    "string": "%s: %s::%s: powering on\n",
                    "segment": "__TEXT",
                    "section": "__cstring",
                    "caller": "__os_log_internal"
                },
                {
                    "string": "%s: %s::%s: failed to load SRAM\n",
                    "segment": "__TEXT",
                    "section": "__cstring",
                    "caller": "__os_log_internal"
                },
                {
                    "string": "%s: %s::%s: powering off\n",
                    "segment": "__TEXT",
                    "section": "__cstring",
                    "caller": "__os_log_internal"
                },
                {
                    "string": "%s: %s::%s: powering on\n",
                    "segment": "__TEXT",
                    "section": "__os_log",
                    "caller": "__os_log_internal"
                },
                {
                    "string": "%s: %s::%s: failed to load SRAM\n",
                    "segment": "__TEXT",
                    "section": "__os_log",
                    "caller": "__os_log_internal"
                },
                {
                    "string": "%s: %s::%s: powering off\n",
                    "segment": "__TEXT",
                    "section": "__os_log",
                    "caller": "__os_log_internal"
                }
            ],
            "symbol": "____ZN17AppleT8027USB3Phy19configurePowerLevelEj23AppleTypeCPhyPowerLevel_block_invoke",
            "prototype": "",
            "backtrace": [],
            "provenance": "direct"
        },
        {
            "args": 0,
            "anchors": [
                {
                    "string": "%s: %s::%s: lane %d is powered off\n",
                    "segment": "__TEXT",
                    "section": "__cstring",
                    "caller": "_IOLog"
                },
                {
                    "string": "%s: %s::%s: unexpected reset state\n",
                    "segment": "__TEXT",
                    "section": "__cstring",
                    "caller": "_IOLog"
                },
                {
                    "string": "%s: %s::%s: mode %d -> %d\n",
                    "segment": "__TEXT",
                    "section": "__cstring",
                    "caller": "_IOLog"
                },
                {
                    "string": "%s: %s::%s: lane %d is powered off\n",
                    "segment": "__TEXT",
                    "section": "__os_log",
                    "caller": "__os_log_internal"
                },
                {
                    "string": "%s: %s::%s: unexpected reset state\n",
                    "segment": "__TEXT",
                    "section": "__os_log",
                    "caller": "__os_log_internal"
                },
                {
                    "string": "%s: %s::%s: mode %d -> %d\n",
                    "segment": "__TEXT",
                    "section": "__os_log",
                    "caller": "__os_log_internal"
                }
            ],
            "symbol": "____ZN17AppleT8027USB3Phy13configureModeEj20AppleTypeCPhyUSBMode_block_invoke",
            "prototype": "",
            "backtrace": [],
            "provenance": "direct"
        },
        {
            "args": 0,
            "anchors": [
                {
                    "string": "applyUSB3PhySettings",
                    "segment": "__TEXT",
                    "section": "__cstring",
                    "caller": "__os_log_internal"
                }
            ],
            "symbol": "__ZN17AppleT8027USB3Phy20applyUSB3PhySettingsEv",
            "prototype": "",
            "backtrace": [
                "____ZN17AppleT8027USB3Phy19configurePowerLevelEj23AppleTypeCPhyPowerLevel_block_invoke"
            ],
            "provenance": "direct"
        },
        {
            "args": 0,
            "anchors": [
                {
                    "string": "%s: %s::%s: USB_PS 0x%08x -> 0x%08x\n",
                    "segment": "__TEXT",
                    "section": "__cstring",
                    "caller": "__os_log_internal"
                },
                {
                    "string": "%s: %s::%s: unexpected USB_PS 0x%08x\n",
                    "segment": "__TEXT",
                    "section": "__cstring",
                    "caller": "_IOLog"
                },
                {
                    "string": "%s: %s::%s: USB_PS 0x%08x -> 0x%08x\n",
                    "segment": "__TEXT",
                    "section": "__os_log",
                    "caller": "__os_log_internal"
                },
                {
                    "string": "%s: %s::%s: unexpected USB_PS 0x%08x\n",
                    "segment": "__TEXT",
                    "section": "__os_log",
                    "caller": "__os_log_internal"
                }
            ],
            "symbol": "__ZN17AppleT8027USB3Phy21disableLowLeakageModeEv",
            "prototype": "",
            "backtrace": [],
            "provenance": "direct"
        },
        {
            "args": 0,
            "anchors": [],
            "symbol": "_panic",
            "prototype": "",
            "backtrace": [
                "_OUTLINED_FUNCTION_0"
            ],
            "provenance": "propagated"
        },
        {
            "args": 0,
            "anchors": [
                {
                    "string": "AppleT8027USB3Phy.cpp",
                    "segment": "__TEXT",
                    "section": "__cstring",
                    "caller": "_OUTLINED_FUNCTION_0"
                }
            ],
            "symbol": "__ZN17AppleT8027USB3Phy21disableLowLeakageModeEv.cold.1",
            "prototype": "",
            "backtrace": [],
            "provenance": "weak-string+callee"
        },
        {
            "args": 0,
            "anchors": [
                {
                    "string": "AppleT8027USB3Phy.cpp",
                    "segment": "__TEXT",
                    "section": "__cstring",
                    "caller": "_OUTLINED_FUNCTION_0"
                }
            ],
            "symbol": "____ZN17AppleT8027USB3Phy19configurePowerLevelEj23AppleTypeCPhyPowerLevel_block_invoke.cold.1",
            "prototype": "",
            "backtrace": [],
            "provenance": "weak-string+callee"
        },
        {
            "args": 0,
            "anchors": [
                {
                    "string": "AppleT8027USB3Phy.cpp",
                    "segment": "__TEXT",
                    "section": "__cstring",
                    "caller": "_OUTLINED_FUNCTION_0"
                }
            ],
            "symbol": "____ZN17AppleT8027USB3Phy13configureModeEj20AppleTypeCPhyUSBMode_block_invoke.cold.1",
            "prototype": "",
            "backtrace": [],
            "provenance": "weak-string+callee"
        }
    ]
}