{
    "target": "com.apple.driver.AppleUVDMLib",
    "total": 2,
    "version": {
        "max": "25.6.0",
        "min": "25.5.0"
    },
    "signatures": [
        {
            "args": 1,
            "anchors": [
                {
                    "string": "AppleUVDMEndpoint",
                    "segment": "__TEXT",
                    "section": "__cstring",
                    "caller": "_IOObjectConformsTo"
                }
            ],
            "symbol": "__ZN16AppleUVDMLibPriv11probeStaticEPvPK14__CFDictionaryjPi",
            "prototype": "",
            "backtrace": [
                "_IOObjectConformsTo"
            ],
            "provenance": "direct"
        },
        {
            "args": 0,
            "anchors": [],
            "symbol": "_IOObjectConformsTo",
            "prototype": "",
            "backtrace": [
                "__ZN16AppleUVDMLibPriv11probeStaticEPvPK14__CFDictionaryjPi"
            ],
            "provenance": "propagated"
        }
    ]
}