{
    "target": "com.apple.driver.AppleD2460PMU",
    "total": 50,
    "version": {
        "max": "25.5.0",
        "min": "25.3.0"
    },
    "signatures": [
        {
            "args": 2,
            "anchors": [
                {
                    "string": "vdd_main",
                    "segment": "__TEXT",
                    "section": "__cstring",
                    "caller": "_strlcpy"
                },
                {
                    "string": "tjunc",
                    "segment": "__TEXT",
                    "section": "__cstring",
                    "caller": "_strlcpy"
                },
                {
                    "string": "tdev%d",
                    "segment": "__TEXT",
                    "section": "__cstring",
                    "caller": "_snprintf"
                },
                {
                    "string": "ldo4_temp",
                    "segment": "__TEXT",
                    "section": "__cstring",
                    "caller": "_strlcpy"
                },
                {
                    "string": "buck%d_temp",
                    "segment": "__TEXT",
                    "section": "__cstring",
                    "caller": "_snprintf"
                },
                {
                    "string": "ldo%d",
                    "segment": "__TEXT",
                    "section": "__cstring",
                    "caller": "_snprintf"
                },
                {
                    "string": "vbuck%d",
                    "segment": "__TEXT",
                    "section": "__cstring",
                    "caller": "_snprintf"
                },
                {
                    "string": "sw3%c",
                    "segment": "__TEXT",
                    "section": "__cstring",
                    "caller": "_snprintf"
                },
                {
                    "string": "app_mux",
                    "segment": "__TEXT",
                    "section": "__cstring",
                    "caller": "_strlcpy"
                }
            ],
            "symbol": "__ZN13AppleD2460PMU14_getSensorInfoEjPcmS0_S0_S0_",
            "prototype": "",
            "backtrace": [
                "__ZN13AppleD2460PMU16_createADCSensorEj",
                "__ZN13AppleD2460PMU5startEP9IOService"
            ],
            "provenance": "direct"
        },
        {
            "args": 0,
            "anchors": [
                {
                    "string": "%s::%s: ADC chan %ld: data=%x\n",
                    "segment": "__TEXT",
                    "section": "__cstring",
                    "caller": "_IOLog"
                },
                {
                    "string": "%s::%s: ADC chan %ld: Vntc=%ld, Rntc=%ld T=%ld\n",
                    "segment": "__TEXT",
                    "section": "__cstring",
                    "caller": "_IOLog"
                },
                {
                    "string": "%s::%s: ADC chan %ld: offset=%d, value=%ld, T=%ld\n",
                    "segment": "__TEXT",
                    "section": "__cstring",
                    "caller": "_IOLog"
                },
                {
                    "string": "%s::%s: ADC chan %ld: value=%ld, T=%ld\n",
                    "segment": "__TEXT",
                    "section": "__cstring",
                    "caller": "_IOLog"
                }
            ],
            "symbol": "__ZN13AppleD2460PMU26_determineTemperatureGatedEjPi",
            "prototype": "",
            "backtrace": [],
            "provenance": "direct"
        },
        {
            "args": 0,
            "anchors": [
                {
                    "string": "%s::%s: ADC chan %ld: value=%d current=%x (result=%x)\n",
                    "segment": "__TEXT",
                    "section": "__cstring",
                    "caller": "_IOLog"
                },
                {
                    "string": "_determineCurrentGated",
                    "segment": "__TEXT",
                    "section": "__cstring",
                    "caller": "_IOLog"
                }
            ],
            "symbol": "__ZN13AppleD2460PMU22_determineCurrentGatedEjPi",
            "prototype": "",
            "backtrace": [],
            "provenance": "direct"
        },
        {
            "args": 0,
            "anchors": [
                {
                    "string": "%s:%d cannot enter test mode (%#x)\n",
                    "segment": "__TEXT",
                    "section": "__cstring",
                    "caller": "_IOLog"
                },
                {
                    "string": "AppleD2460PMU.cpp",
                    "segment": "__TEXT",
                    "section": "__cstring",
                    "caller": "_panic"
                }
            ],
            "symbol": "__ZN13AppleD2460PMU22setChargerVbatRechargeEv",
            "prototype": "",
            "backtrace": [
                "__ZN35AppleD2460PMURegisterAccessFunction12callFunctionEPvS0_S0_"
            ],
            "provenance": "direct"
        },
        {
            "args": 0,
            "anchors": [
                {
                    "string": "IOPMUSetBootStagePanicSafe",
                    "segment": "__TEXT",
                    "section": "__cstring",
                    "caller": "__ZN8OSSymbol17withCStringNoCopyEPKc"
                },
                {
                    "string": "IOPMUDisableResetIn2",
                    "segment": "__TEXT",
                    "section": "__cstring",
                    "caller": "__ZN8OSSymbol17withCStringNoCopyEPKc"
                }
            ],
            "symbol": "__GLOBAL__sub_I_AppleDialogClassPMU.cpp",
            "prototype": "",
            "backtrace": [],
            "provenance": "direct"
        },
        {
            "args": 0,
            "anchors": [
                {
                    "string": "AppleD2460PMU::start: %s _pmuIICNub: %p built 20:36:06 Jan 28 2026\n",
                    "segment": "__TEXT",
                    "section": "__cstring",
                    "caller": "_kprintf"
                },
                {
                    "string": "ibat-sense-mohm",
                    "segment": "__TEXT",
                    "section": "__cstring",
                    "caller": "__ZN15OSMetaClassBase12safeMetaCastEPKS_PK11OSMetaClass"
                },
                {
                    "string": "gpio-activate-defaults",
                    "segment": "__TEXT",
                    "section": "__cstring",
                    "caller": "_kprintf"
                },
                {
                    "string": "gpio-suspend-defaults",
                    "segment": "__TEXT",
                    "section": "__cstring",
                    "caller": "_kprintf"
                },
                {
                    "string": "gpio-quiesce-defaults",
                    "segment": "__TEXT",
                    "section": "__cstring",
                    "caller": "_kprintf"
                },
                {
                    "string": "gpio-pin-config",
                    "segment": "__TEXT",
                    "section": "__cstring",
                    "caller": "_kprintf"
                },
                {
                    "string": "dbl-click-rates",
                    "segment": "__TEXT",
                    "section": "__cstring",
                    "caller": "_kprintf"
                },
                {
                    "string": "spi-buck-control",
                    "segment": "__TEXT",
                    "section": "__cstring",
                    "caller": "_kprintf"
                },
                {
                    "string": "AppleD2460PMU::start: using SPI for BUCK changes (not yet)\n",
                    "segment": "__TEXT",
                    "section": "__cstring",
                    "caller": "_kprintf"
                },
                {
                    "string": "pmu-disable-ulpm",
                    "segment": "__TEXT",
                    "section": "__cstring",
                    "caller": "_PE_parse_boot_argn"
                },
                {
                    "string": "pmu-chargetrap",
                    "segment": "__TEXT",
                    "section": "__cstring",
                    "caller": "_PE_parse_boot_argn"
                },
                {
                    "string": "/chosen",
                    "segment": "__TEXT",
                    "section": "__cstring",
                    "caller": "__ZN15IORegistryEntry8fromPathEPKcPK15IORegistryPlanePcPiPS_"
                },
                {
                    "string": "software-behavior",
                    "segment": "__TEXT",
                    "section": "__cstring",
                    "caller": "__ZN15OSMetaClassBase12safeMetaCastEPKS_PK11OSMetaClass"
                },
                {
                    "string": "IOPMUPrimary",
                    "segment": "__TEXT",
                    "section": "__cstring",
                    "caller": "__ZN9IOService11getPlatformEv"
                },
                {
                    "string": "function-suspend_helper",
                    "segment": "__TEXT",
                    "section": "__cstring",
                    "caller": "__ZN16AppleARMFunction12withProviderEP15IORegistryEntryPKc"
                },
                {
                    "string": "function-external_shutdown",
                    "segment": "__TEXT",
                    "section": "__cstring",
                    "caller": "__ZN16AppleARMFunction12withProviderEP15IORegistryEntryPKc"
                },
                {
                    "string": "function-panic_reset",
                    "segment": "__TEXT",
                    "section": "__cstring",
                    "caller": "__ZN16AppleARMFunction12withProviderEP15IORegistryEntryPKc"
                },
                {
                    "string": "function-get_vbus_detect",
                    "segment": "__TEXT",
                    "section": "__cstring",
                    "caller": "__ZN16AppleARMFunction12withProviderEP15IORegistryEntryPKc"
                },
                {
                    "string": "function-sensor_dfr",
                    "segment": "__TEXT",
                    "section": "__cstring",
                    "caller": "__ZN13AppleD2460PMU16_createADCSensorEj"
                },
                {
                    "string": "start",
                    "segment": "__TEXT",
                    "section": "__cstring",
                    "caller": "__ZNK11OSMetaClass12getClassNameEv"
                }
            ],
            "symbol": "__ZN13AppleD2460PMU5startEP9IOService",
            "prototype": "",
            "backtrace": [],
            "provenance": "direct"
        },
        {
            "args": 0,
            "anchors": [
                {
                    "string": "\"%s::start: gpio-pin-config is sized incorrectly!\\n\" @%s:%d",
                    "segment": "__TEXT",
                    "section": "__cstring",
                    "caller": "_panic"
                }
            ],
            "symbol": "__ZN13AppleD2460PMU5startEP9IOService.cold.1",
            "prototype": "",
            "backtrace": [
                "_panic",
                "__ZN13AppleD2460PMU5startEP9IOService"
            ],
            "provenance": "direct"
        },
        {
            "args": 1,
            "anchors": [
                {
                    "string": "%s::%scannot read GPIO configuration (%#x)\n",
                    "segment": "__TEXT",
                    "section": "__cstring",
                    "caller": "_snprintf"
                },
                {
                    "string": " WAKEINT: ",
                    "segment": "__TEXT",
                    "section": "__cstring",
                    "caller": "_snprintf"
                },
                {
                    "string": " WAKEREA: ",
                    "segment": "__TEXT",
                    "section": "__cstring",
                    "caller": "_snprintf"
                },
                {
                    "string": "_rtc_wake",
                    "segment": "__TEXT",
                    "section": "__cstring",
                    "caller": "_snprintf"
                },
                {
                    "string": "ringerab",
                    "segment": "__TEXT",
                    "section": "__cstring",
                    "caller": "__ZN14AppleDialogPMU18_publishWakeReasonEPKcS1_"
                },
                {
                    "string": "chg_end",
                    "segment": "__TEXT",
                    "section": "__cstring",
                    "caller": "__ZN14AppleDialogPMU18_publishWakeReasonEPKcS1_"
                },
                {
                    "string": "gpio1",
                    "segment": "__TEXT",
                    "section": "__cstring",
                    "caller": "__ZN14AppleDialogPMU18_publishWakeReasonEPKcS1_"
                },
                {
                    "string": "gpio2",
                    "segment": "__TEXT",
                    "section": "__cstring",
                    "caller": "__ZN14AppleDialogPMU18_publishWakeReasonEPKcS1_"
                },
                {
                    "string": "gpio3",
                    "segment": "__TEXT",
                    "section": "__cstring",
                    "caller": "__ZN14AppleDialogPMU18_publishWakeReasonEPKcS1_"
                },
                {
                    "string": "gpio4",
                    "segment": "__TEXT",
                    "section": "__cstring",
                    "caller": "__ZN14AppleDialogPMU18_publishWakeReasonEPKcS1_"
                },
                {
                    "string": "gpio5",
                    "segment": "__TEXT",
                    "section": "__cstring",
                    "caller": "__ZN14AppleDialogPMU18_publishWakeReasonEPKcS1_"
                },
                {
                    "string": "gpio6",
                    "segment": "__TEXT",
                    "section": "__cstring",
                    "caller": "__ZN14AppleDialogPMU18_publishWakeReasonEPKcS1_"
                },
                {
                    "string": "gpio7",
                    "segment": "__TEXT",
                    "section": "__cstring",
                    "caller": "__ZN14AppleDialogPMU18_publishWakeReasonEPKcS1_"
                },
                {
                    "string": "gpio8",
                    "segment": "__TEXT",
                    "section": "__cstring",
                    "caller": "__ZN14AppleDialogPMU18_publishWakeReasonEPKcS1_"
                },
                {
                    "string": "gpio9",
                    "segment": "__TEXT",
                    "section": "__cstring",
                    "caller": "__ZN14AppleDialogPMU18_publishWakeReasonEPKcS1_"
                },
                {
                    "string": "gpio10",
                    "segment": "__TEXT",
                    "section": "__cstring",
                    "caller": "__ZN14AppleDialogPMU18_publishWakeReasonEPKcS1_"
                },
                {
                    "string": "gpio11",
                    "segment": "__TEXT",
                    "section": "__cstring",
                    "caller": "__ZN14AppleDialogPMU18_publishWakeReasonEPKcS1_"
                },
                {
                    "string": "gpio12",
                    "segment": "__TEXT",
                    "section": "__cstring",
                    "caller": "__ZN14AppleDialogPMU18_publishWakeReasonEPKcS1_"
                },
                {
                    "string": "gpio13",
                    "segment": "__TEXT",
                    "section": "__cstring",
                    "caller": "__ZN14AppleDialogPMU18_publishWakeReasonEPKcS1_"
                },
                {
                    "string": "gpio14",
                    "segment": "__TEXT",
                    "section": "__cstring",
                    "caller": "__ZN14AppleDialogPMU18_publishWakeReasonEPKcS1_"
                },
                {
                    "string": "gpio15",
                    "segment": "__TEXT",
                    "section": "__cstring",
                    "caller": "__ZN14AppleDialogPMU18_publishWakeReasonEPKcS1_"
                },
                {
                    "string": "gpio16",
                    "segment": "__TEXT",
                    "section": "__cstring",
                    "caller": "__ZN14AppleDialogPMU18_publishWakeReasonEPKcS1_"
                },
                {
                    "string": "gpio17",
                    "segment": "__TEXT",
                    "section": "__cstring",
                    "caller": "__ZN14AppleDialogPMU18_publishWakeReasonEPKcS1_"
                },
                {
                    "string": "gpio18",
                    "segment": "__TEXT",
                    "section": "__cstring",
                    "caller": "__ZN14AppleDialogPMU18_publishWakeReasonEPKcS1_"
                },
                {
                    "string": "gpio19",
                    "segment": "__TEXT",
                    "section": "__cstring",
                    "caller": "__ZN14AppleDialogPMU18_publishWakeReasonEPKcS1_"
                },
                {
                    "string": "gpio20",
                    "segment": "__TEXT",
                    "section": "__cstring",
                    "caller": "__ZN14AppleDialogPMU18_publishWakeReasonEPKcS1_"
                },
                {
                    "string": "gpio21",
                    "segment": "__TEXT",
                    "section": "__cstring",
                    "caller": "__ZN14AppleDialogPMU18_publishWakeReasonEPKcS1_"
                },
                {
                    "string": "gpio22",
                    "segment": "__TEXT",
                    "section": "__cstring",
                    "caller": "__ZN14AppleDialogPMU18_publishWakeReasonEPKcS1_"
                },
                {
                    "string": "%s: late vbus detect. scheduling rtc immediate wake\n",
                    "segment": "__TEXT",
                    "section": "__cstring",
                    "caller": "_IOLog"
                },
                {
                    "string": "%s::%s cannot read GPIO config (%#x)\n",
                    "segment": "__TEXT",
                    "section": "__cstring",
                    "caller": "_IOLog"
                },
                {
                    "string": " EVENTS : ",
                    "segment": "__TEXT",
                    "section": "__cstring",
                    "caller": "_IOLog"
                },
                {
                    "string": " IRQMASK: ",
                    "segment": "__TEXT",
                    "section": "__cstring",
                    "caller": "_IOLog"
                },
                {
                    "string": "pmu go hib (0x%x)\n",
                    "segment": "__TEXT",
                    "section": "__cstring",
                    "caller": "_IOLog"
                }
            ],
            "symbol": "__ZN13AppleD2460PMU20callPlatformFunctionEPK8OSSymbolbPvS3_S3_S3_",
            "prototype": "",
            "backtrace": [],
            "provenance": "direct"
        },
        {
            "args": 0,
            "anchors": [
                {
                    "string": "info-fault_name-1",
                    "segment": "__TEXT",
                    "section": "__cstring",
                    "caller": "__ZN15OSMetaClassBase12safeMetaCastEPKS_PK11OSMetaClass"
                },
                {
                    "string": "info-fault_name-2",
                    "segment": "__TEXT",
                    "section": "__cstring",
                    "caller": "__ZN15OSMetaClassBase12safeMetaCastEPKS_PK11OSMetaClass"
                },
                {
                    "string": "dbg_rst",
                    "segment": "__TEXT",
                    "section": "__cstring",
                    "caller": "__ZN8OSString11withCStringEPKc"
                },
                {
                    "string": "over_temp",
                    "segment": "__TEXT",
                    "section": "__cstring",
                    "caller": "_IOLog"
                },
                {
                    "string": "vdd_under",
                    "segment": "__TEXT",
                    "section": "__cstring",
                    "caller": "_IOLog"
                },
                {
                    "string": "ntc_shdn",
                    "segment": "__TEXT",
                    "section": "__cstring",
                    "caller": "_IOLog"
                },
                {
                    "string": "btn_shdn",
                    "segment": "__TEXT",
                    "section": "__cstring",
                    "caller": "_IOLog"
                },
                {
                    "string": "btn_rst",
                    "segment": "__TEXT",
                    "section": "__cstring",
                    "caller": "_IOLog"
                },
                {
                    "string": "pmu fault log:%s\n",
                    "segment": "__TEXT",
                    "section": "__cstring",
                    "caller": "_IOLog"
                },
                {
                    "string": "IOPMUBootFaultInfo",
                    "segment": "__TEXT",
                    "section": "__cstring",
                    "caller": "__ZN7OSArray12withCapacityEj"
                }
            ],
            "symbol": "__ZN13AppleD2460PMU21_updateFaultRegistersEb",
            "prototype": "",
            "backtrace": [
                "__ZN13AppleD2460PMU21_updateBootPropertiesEb"
            ],
            "provenance": "direct"
        },
        {
            "args": 0,
            "anchors": [
                {
                    "string": "IOPMUBootErrorAppName",
                    "segment": "__TEXT",
                    "section": "__cstring",
                    "caller": "__ZN13AppleD2460PMU21_updateFaultRegistersEb"
                },
                {
                    "string": "IOPMUBootErrorClear",
                    "segment": "__TEXT",
                    "section": "__cstring",
                    "caller": null
                },
                {
                    "string": "IOPMUBootAppName",
                    "segment": "__TEXT",
                    "section": "__cstring",
                    "caller": null
                },
                {
                    "string": "IOPMUBootErrorFailCount",
                    "segment": "__TEXT",
                    "section": "__cstring",
                    "caller": null
                },
                {
                    "string": "IOPMUBootErrorPanicCount",
                    "segment": "__TEXT",
                    "section": "__cstring",
                    "caller": null
                },
                {
                    "string": "IOPMUBootDebug",
                    "segment": "__TEXT",
                    "section": "__cstring",
                    "caller": null
                }
            ],
            "symbol": "__ZN13AppleD2460PMU21_updateBootPropertiesEb",
            "prototype": "",
            "backtrace": [
                "__ZN13AppleD2460PMU21_updateFaultRegistersEb"
            ],
            "provenance": "direct"
        },
        {
            "args": 0,
            "anchors": [
                {
                    "string": "AppleD2460PMU: LUTInterpolate: R=%ld, R1=%ld, R2=%ld, T1=%ld, T2=%ld\n",
                    "segment": "__TEXT",
                    "section": "__cstring",
                    "caller": "_IOLog"
                }
            ],
            "symbol": "__ZNK13AppleD2460PMU14LUTInterpolateEPK6NTCLUTj",
            "prototype": "",
            "backtrace": [
                "_IOLog",
                "__ZN13AppleD2460PMU26_determineTemperatureGatedEjPi"
            ],
            "provenance": "direct"
        },
        {
            "args": 0,
            "anchors": [
                {
                    "string": "AppleD2460PMU::_setLDO: index=%02x, ldo%d, voltage=%d, options=%lx, enable=%d\n",
                    "segment": "__TEXT",
                    "section": "__cstring",
                    "caller": "_kprintf"
                }
            ],
            "symbol": "__ZN13AppleD2460PMU7_setLDOEhtjb",
            "prototype": "",
            "backtrace": [],
            "provenance": "direct"
        },
        {
            "args": 0,
            "anchors": [
                {
                    "string": " GPIODFL: ",
                    "segment": "__TEXT",
                    "section": "__cstring",
                    "caller": "__ZL10dumpBufferPKcPhm"
                }
            ],
            "symbol": "__ZN13AppleD2460PMU16_setGPIODefaultsEPh",
            "prototype": "",
            "backtrace": [],
            "provenance": "direct"
        },
        {
            "args": 0,
            "anchors": [
                {
                    "string": "AppleD2460PMU::_setGPIOFunction: unsupported function, %d\n",
                    "segment": "__TEXT",
                    "section": "__cstring",
                    "caller": "_IOLog"
                }
            ],
            "symbol": "__ZN13AppleD2460PMU16_setGPIOFunctionEjhb",
            "prototype": "",
            "backtrace": [
                "__ZN25AppleD2460PMUGPIOFunction12callFunctionEPvS0_S0_"
            ],
            "provenance": "direct"
        },
        {
            "args": 0,
            "anchors": [
                {
                    "string": "pmu bootErrorStage=%x\n",
                    "segment": "__TEXT",
                    "section": "__cstring",
                    "caller": "_IOLog"
                },
                {
                    "string": "System shutdown complete\n",
                    "segment": "__TEXT",
                    "section": "__cstring",
                    "caller": "_IOLog"
                },
                {
                    "string": "AppleARMPMUPowerSource",
                    "segment": "__TEXT",
                    "section": "__cstring",
                    "caller": "_kprintf"
                },
                {
                    "string": "standbyok %d\n",
                    "segment": "__TEXT",
                    "section": "__cstring",
                    "caller": "_kprintf"
                },
                {
                    "string": "upo error (%x)\n",
                    "segment": "__TEXT",
                    "section": "__cstring",
                    "caller": "_kprintf"
                },
                {
                    "string": "upo clear\n",
                    "segment": "__TEXT",
                    "section": "__cstring",
                    "caller": "_kprintf"
                },
                {
                    "string": "upo: wake in %d\n",
                    "segment": "__TEXT",
                    "section": "__cstring",
                    "caller": "_kprintf"
                },
                {
                    "string": "upo: standbyok=%d\n",
                    "segment": "__TEXT",
                    "section": "__cstring",
                    "caller": "_kprintf"
                },
                {
                    "string": "%s:%d cannot turn off GPIO wakes\n",
                    "segment": "__TEXT",
                    "section": "__cstring",
                    "caller": "_kprintf"
                },
                {
                    "string": "_shutdownGated",
                    "segment": "__TEXT",
                    "section": "__cstring",
                    "caller": "_kprintf"
                },
                {
                    "string": "%s:%d cannot clear Events\n",
                    "segment": "__TEXT",
                    "section": "__cstring",
                    "caller": "_kprintf"
                },
                {
                    "string": "pmu go stdby\n",
                    "segment": "__TEXT",
                    "section": "__cstring",
                    "caller": "_kprintf"
                },
                {
                    "string": "utc-offset",
                    "segment": "__TEXT",
                    "section": "__cstring",
                    "caller": "__ZN9IOService15serviceMatchingEPKcP12OSDictionary"
                },
                {
                    "string": "display_nonUI",
                    "segment": "__TEXT",
                    "section": "__cstring",
                    "caller": "__ZN9IOService15serviceMatchingEPKcP12OSDictionary"
                },
                {
                    "string": "pmu restarting\n",
                    "segment": "__TEXT",
                    "section": "__cstring",
                    "caller": "_kprintf"
                }
            ],
            "symbol": "__ZN13AppleD2460PMU14_shutdownGatedEv",
            "prototype": "",
            "backtrace": [],
            "provenance": "direct"
        },
        {
            "args": 0,
            "anchors": [
                {
                    "string": "AppleVoltageDictionary",
                    "segment": "__TEXT",
                    "section": "__cstring",
                    "caller": "_strcmp"
                },
                {
                    "string": "AppleRegisterDump",
                    "segment": "__TEXT",
                    "section": "__cstring",
                    "caller": "_strcmp"
                }
            ],
            "symbol": "__ZN13AppleD2460PMU17copyDebugPropertyEPKc",
            "prototype": "",
            "backtrace": [],
            "provenance": "direct"
        },
        {
            "args": 0,
            "anchors": [
                {
                    "string": "AppleD2460PMU::_setLDO: index=%02x, ldo%d, voltage=%d, options=%lx, enable=%d (placeholder)\n",
                    "segment": "__TEXT",
                    "section": "__cstring",
                    "caller": "_kprintf"
                }
            ],
            "symbol": "__ZN24AppleD2460PMULDOFunction12callFunctionEPvS0_S0_",
            "prototype": "",
            "backtrace": [],
            "provenance": "direct"
        },
        {
            "args": 0,
            "anchors": [
                {
                    "string": "AppleD2460PMULDOFunction::%s: ldo%d illegal device tree options\n",
                    "segment": "__TEXT",
                    "section": "__cstring",
                    "caller": "_IOLog"
                },
                {
                    "string": "AppleD2460PMU::_setLDO: index=%02x, ldo%d, voltage=%d, options=%lx, enable=%d (init placeholder)\n",
                    "segment": "__TEXT",
                    "section": "__cstring",
                    "caller": "_kprintf"
                },
                {
                    "string": "AppleD2460PMULDOFunction::%s: ldo%d failed first _setLDO\n",
                    "segment": "__TEXT",
                    "section": "__cstring",
                    "caller": "_IOLog"
                }
            ],
            "symbol": "__ZN24AppleD2460PMULDOFunction27initWithTargetDataAndSymbolEP9IOServicePK6OSDataPK8OSSymbol",
            "prototype": "",
            "backtrace": [],
            "provenance": "direct"
        },
        {
            "args": 0,
            "anchors": [
                {
                    "string": "\"cannot exit PMU test mode (%x)\" @%s:%d",
                    "segment": "__TEXT",
                    "section": "__cstring",
                    "caller": "_panic"
                }
            ],
            "symbol": "__ZN35AppleD2460PMURegisterAccessFunction12callFunctionEPvS0_S0_",
            "prototype": "",
            "backtrace": [],
            "provenance": "direct"
        },
        {
            "args": 0,
            "anchors": [
                {
                    "string": "%s::%scannot initialize reg %x (%x)\n",
                    "segment": "__TEXT",
                    "section": "__cstring",
                    "caller": "_IOLog"
                }
            ],
            "symbol": "__ZN35AppleD2460PMURegisterAccessFunction27initWithTargetDataAndSymbolEP9IOServicePK6OSDataPK8OSSymbol",
            "prototype": "",
            "backtrace": [],
            "provenance": "direct"
        },
        {
            "args": 0,
            "anchors": [
                {
                    "string": ":%02x",
                    "segment": "__TEXT",
                    "section": "__cstring",
                    "caller": "_snprintf"
                },
                {
                    "string": "AppleD2460PMU%s %d %s\n",
                    "segment": "__TEXT",
                    "section": "__cstring",
                    "caller": "_IOLog"
                }
            ],
            "symbol": "__ZL10dumpBufferPKcPhm",
            "prototype": "",
            "backtrace": [],
            "provenance": "direct"
        },
        {
            "args": 0,
            "anchors": [
                {
                    "string": "pmu-debug",
                    "segment": "__TEXT",
                    "section": "__cstring",
                    "caller": "_PE_parse_boot_argn"
                },
                {
                    "string": "pmu-bringup",
                    "segment": "__TEXT",
                    "section": "__cstring",
                    "caller": "_PE_parse_boot_argn"
                },
                {
                    "string": "usb-input-limit-calibration",
                    "segment": "__TEXT",
                    "section": "__cstring",
                    "caller": "__ZN15OSMetaClassBase12safeMetaCastEPKS_PK11OSMetaClass"
                },
                {
                    "string": "function-set_dbgpwr",
                    "segment": "__TEXT",
                    "section": "__cstring",
                    "caller": "__ZN16AppleARMFunction12withProviderEP15IORegistryEntryPKc"
                }
            ],
            "symbol": "__ZN24AppleD2460PMUPowerSource13attachChargerEP9IOService",
            "prototype": "",
            "backtrace": [],
            "provenance": "direct"
        },
        {
            "args": 1,
            "anchors": [
                {
                    "string": "AppleD2460PMUPowerSource::handleInterrupt(%#x)\n",
                    "segment": "__TEXT",
                    "section": "__cstring",
                    "caller": "_IOLog"
                }
            ],
            "symbol": "__ZN24AppleD2460PMUPowerSource15handleInterruptEt",
            "prototype": "",
            "backtrace": [],
            "provenance": "direct"
        },
        {
            "args": 0,
            "anchors": [
                {
                    "string": "AppleForceResetEndOfCharge",
                    "segment": "__TEXT",
                    "section": "__cstring",
                    "caller": "_IOLog"
                },
                {
                    "string": "AppleD2460PMUPowerSource::%s resetting end of charge\n",
                    "segment": "__TEXT",
                    "section": "__cstring",
                    "caller": "_IOLog"
                },
                {
                    "string": "setDebugProperties",
                    "segment": "__TEXT",
                    "section": "__cstring",
                    "caller": "_IOLog"
                }
            ],
            "symbol": "__ZN24AppleD2460PMUPowerSource18setDebugPropertiesEPK12OSDictionary",
            "prototype": "",
            "backtrace": [
                "_IOLog"
            ],
            "provenance": "direct"
        },
        {
            "args": 0,
            "anchors": [
                {
                    "string": "ChargePowerPath",
                    "segment": "__TEXT",
                    "section": "__cstring",
                    "caller": "_panic"
                },
                {
                    "string": "AppleD2460PMUPowerSource::%s ChargePowerPath: not supported\n",
                    "segment": "__TEXT",
                    "section": "__cstring",
                    "caller": "_snprintf"
                },
                {
                    "string": "AppleD2460PMUPowerSource::%s ChargePowerPath: configured GPIO to %d\n",
                    "segment": "__TEXT",
                    "section": "__cstring",
                    "caller": "_snprintf"
                },
                {
                    "string": "pwr-path",
                    "segment": "__TEXT",
                    "section": "__cstring",
                    "caller": "_snprintf"
                },
                {
                    "string": "IONVRAM-FORCESYNCNOW-PROPERTY",
                    "segment": "__TEXT",
                    "section": "__cstring",
                    "caller": "_panic"
                },
                {
                    "string": "AppleD2460PMUPowerSource::%s ChargePowerPath: pwr-path set to %d\n",
                    "segment": "__TEXT",
                    "section": "__cstring",
                    "caller": "_panic"
                },
                {
                    "string": "AppleD2460PMUPowerSource::%s ChargePowerPath: failed to set pwr-path to %d\n",
                    "segment": "__TEXT",
                    "section": "__cstring",
                    "caller": "_panic"
                },
                {
                    "string": "ChargeLimitTBATMAX50",
                    "segment": "__TEXT",
                    "section": "__cstring",
                    "caller": "_panic"
                },
                {
                    "string": "AppleD2460PMUPowerSource::%s cannot enter test mode (%#x)\n\n",
                    "segment": "__TEXT",
                    "section": "__cstring",
                    "caller": "_IOLog"
                },
                {
                    "string": "AppleD2460PMUPowerSource::%s cannot reset TBAT_MAX (%#x)\n\n",
                    "segment": "__TEXT",
                    "section": "__cstring",
                    "caller": "_panic"
                },
                {
                    "string": "AppleD2460PMUPowerSource::%s changed TBAT_MAX to 0x%x\n\n",
                    "segment": "__TEXT",
                    "section": "__cstring",
                    "caller": "_panic"
                },
                {
                    "string": "AppleDialogPMUPowerSource.cpp",
                    "segment": "__TEXT",
                    "section": "__cstring",
                    "caller": "_panic"
                },
                {
                    "string": "atvAbsMaxVoltageMV",
                    "segment": "__TEXT",
                    "section": "__cstring",
                    "caller": "_IOLog"
                },
                {
                    "string": "AppleD2460PMUPowerSource::%s  atvVoltageMV=%d (VSET_LSB=0x0608=0x%x, result=%x)\n\n",
                    "segment": "__TEXT",
                    "section": "__cstring",
                    "caller": "_IOLog"
                },
                {
                    "string": "AppleD2460PMUPowerSource::%s  atvVoltageMV=%d (VSET_MSB=0x0607=0x%x, result=%x)\n\n",
                    "segment": "__TEXT",
                    "section": "__cstring",
                    "caller": "_IOLog"
                }
            ],
            "symbol": "__ZN24AppleD2460PMUPowerSource20setChargerPropertiesEPK12OSDictionary",
            "prototype": "",
            "backtrace": [],
            "provenance": "direct"
        },
        {
            "args": 0,
            "anchors": [
                {
                    "string": "AppleD2460PMUPowerSource::%s chargeCurrentLimitMA=%d  to (reg: 0x%x=0x%x)\n",
                    "segment": "__TEXT",
                    "section": "__cstring",
                    "caller": "_IOLog"
                },
                {
                    "string": "setChargeCurrentLimit",
                    "segment": "__TEXT",
                    "section": "__cstring",
                    "caller": "_IOLog"
                }
            ],
            "symbol": "__ZN24AppleD2460PMUPowerSource21setChargeCurrentLimitEbjPj",
            "prototype": "",
            "backtrace": [
                "_IOLog"
            ],
            "provenance": "direct"
        },
        {
            "args": 1,
            "anchors": [
                {
                    "string": "pmu-debug-rtc",
                    "segment": "__TEXT",
                    "section": "__cstring",
                    "caller": "_IOLog"
                },
                {
                    "string": "%s::%s [%02x%02x%02x%02x][%02x%02x] _currentOffsetTicks=%lld\n",
                    "segment": "__TEXT",
                    "section": "__cstring",
                    "caller": "_IOLog"
                },
                {
                    "string": "handleStart",
                    "segment": "__TEXT",
                    "section": "__cstring",
                    "caller": "_IOLog"
                }
            ],
            "symbol": "__ZN16AppleD2460PMURTC11handleStartEP9IOService",
            "prototype": "",
            "backtrace": [],
            "provenance": "direct"
        },
        {
            "args": 0,
            "anchors": [
                {
                    "string": "CLASSN(PMURTC)\"::getCurrentDateTime() should not be called\" @%s:%d",
                    "segment": "__TEXT",
                    "section": "__cstring",
                    "caller": "_panic"
                }
            ],
            "symbol": "__ZN16AppleD2460PMURTC18getCurrentDateTimeEP11RTCDateTime",
            "prototype": "",
            "backtrace": [
                "_panic"
            ],
            "provenance": "direct"
        },
        {
            "args": 0,
            "anchors": [
                {
                    "string": "CLASSN(PMURTC)\"::setCurrentDateTime() should not be called\" @%s:%d",
                    "segment": "__TEXT",
                    "section": "__cstring",
                    "caller": "_panic"
                }
            ],
            "symbol": "__ZN16AppleD2460PMURTC18setCurrentDateTimeEPK11RTCDateTime",
            "prototype": "",
            "backtrace": [
                "_panic"
            ],
            "provenance": "direct"
        },
        {
            "args": 0,
            "anchors": [
                {
                    "string": "setChargerWakeAlarm",
                    "segment": "__TEXT",
                    "section": "__cstring",
                    "caller": null
                }
            ],
            "symbol": "__ZN16AppleD2460PMURTC20callPlatformFunctionEPK8OSSymbolbPvS3_S3_S3_",
            "prototype": "",
            "backtrace": [],
            "provenance": "direct"
        },
        {
            "args": 0,
            "anchors": [],
            "symbol": "_panic",
            "prototype": "",
            "backtrace": [
                "__ZN16AppleD2460PMURTC18setCurrentDateTimeEPK11RTCDateTime"
            ],
            "provenance": "propagated"
        },
        {
            "args": 0,
            "anchors": [],
            "symbol": "__ZN13AppleD2460PMU16_createADCSensorEj",
            "prototype": "",
            "backtrace": [
                "__ZN13AppleD2460PMU14_getSensorInfoEjPcmS0_S0_S0_"
            ],
            "provenance": "propagated"
        },
        {
            "args": 0,
            "anchors": [],
            "symbol": "_IOLog",
            "prototype": "",
            "backtrace": [
                "__ZN24AppleD2460PMUPowerSource18setDebugPropertiesEPK12OSDictionary"
            ],
            "provenance": "propagated"
        },
        {
            "args": 0,
            "anchors": [],
            "symbol": "__ZN25AppleD2460PMUGPIOFunction12callFunctionEPvS0_S0_",
            "prototype": "",
            "backtrace": [
                "__ZN13AppleD2460PMU16_setGPIOFunctionEjhb"
            ],
            "provenance": "propagated"
        },
        {
            "args": 1,
            "anchors": [
                {
                    "string": "IOPMUBootStage",
                    "segment": "__TEXT",
                    "section": "__cstring",
                    "caller": "__ZN13AppleD2460PMU21_updateBootPropertiesEb"
                }
            ],
            "symbol": "__ZN13AppleD2460PMU13setPropertiesEP8OSObject",
            "prototype": "",
            "backtrace": [],
            "provenance": "dual-evidence"
        }
    ]
}